aws_easy_use/__init__.py
aws_easy_use/cloudfront.py
aws_easy_use/ecr.py
aws_easy_use/route53.py
aws_easy_use/s3.py
aws_easy_use/secret_manager.py
aws_easy_use/ssm.py
aws_easy_use/sts.py
aws_easy_use/aws_waiter/__init__.py
aws_easy_use/aws_waiter/waiter_ecs_service_primary_deployment_completed.py
aws_easy_use/ecs/__init__.py
aws_easy_use/ecs/cluster.py
aws_easy_use/ecs/codedeploy.py
aws_easy_use/ecs/scheduled_task.py
aws_easy_use/ecs/service.py
aws_easy_use/ecs/task_definition.py
aws_easy_use-0.1.0.dist-info/LICENSE
aws_easy_use-0.1.0.dist-info/METADATA
aws_easy_use-0.1.0.dist-info/WHEEL
aws_easy_use-0.1.0.dist-info/top_level.txt
aws_easy_use-0.1.0.dist-info/RECORD
