Metadata-Version: 2.1
Name: aws-easy-use
Version: 0.1.0
Summary: AWS boto3 wrapper. Make it easier and intuitive to use.
Home-page: https://github.com/imaging8896/aws-easy-use
Author: Ted Chen
Author-email: imaging8896@gmail.com
License: MIT
Project-URL: Source, https://github.com/imaging8896/aws-easy-use
Classifier: Development Status :: 1 - Planning
Classifier: Topic :: Utilities
Classifier: License :: OSI Approved :: MIT License
Classifier: Intended Audience :: System Administrators
Classifier: Intended Audience :: Developers
Classifier: Programming Language :: Python :: 3 :: Only
Requires-Python: >=3
License-File: LICENSE
Requires-Dist: boto3 (>=1.24.28)
